compiler_gym-0.2.5.data/purelib/compiler_gym/__init__.py
compiler_gym-0.2.5.data/purelib/compiler_gym/compiler_env_state.py
compiler_gym-0.2.5.data/purelib/compiler_gym/config.py
compiler_gym-0.2.5.data/purelib/compiler_gym/random_search.py
compiler_gym-0.2.5.data/purelib/compiler_gym/validate.py
compiler_gym-0.2.5.data/purelib/compiler_gym/validation_error.py
compiler_gym-0.2.5.data/purelib/compiler_gym/validation_result.py
compiler_gym-0.2.5.data/purelib/compiler_gym/bin/__init__.py
compiler_gym-0.2.5.data/purelib/compiler_gym/bin/manual_env.py
compiler_gym-0.2.5.data/purelib/compiler_gym/bin/random_replay.py
compiler_gym-0.2.5.data/purelib/compiler_gym/bin/random_search.py
compiler_gym-0.2.5.data/purelib/compiler_gym/bin/service.py
compiler_gym-0.2.5.data/purelib/compiler_gym/bin/validate.py
compiler_gym-0.2.5.data/purelib/compiler_gym/datasets/__init__.py
compiler_gym-0.2.5.data/purelib/compiler_gym/datasets/benchmark.py
compiler_gym-0.2.5.data/purelib/compiler_gym/datasets/dataset.py
compiler_gym-0.2.5.data/purelib/compiler_gym/datasets/datasets.py
compiler_gym-0.2.5.data/purelib/compiler_gym/datasets/files_dataset.py
compiler_gym-0.2.5.data/purelib/compiler_gym/datasets/tar_dataset.py
compiler_gym-0.2.5.data/purelib/compiler_gym/datasets/uri.py
compiler_gym-0.2.5.data/purelib/compiler_gym/envs/__init__.py
compiler_gym-0.2.5.data/purelib/compiler_gym/envs/compiler_env.py
compiler_gym-0.2.5.data/purelib/compiler_gym/envs/gcc/__init__.py
compiler_gym-0.2.5.data/purelib/compiler_gym/envs/gcc/gcc.py
compiler_gym-0.2.5.data/purelib/compiler_gym/envs/gcc/gcc_env.py
compiler_gym-0.2.5.data/purelib/compiler_gym/envs/gcc/gcc_rewards.py
compiler_gym-0.2.5.data/purelib/compiler_gym/envs/gcc/datasets/__init__.py
compiler_gym-0.2.5.data/purelib/compiler_gym/envs/gcc/datasets/anghabench.py
compiler_gym-0.2.5.data/purelib/compiler_gym/envs/gcc/datasets/chstone.py
compiler_gym-0.2.5.data/purelib/compiler_gym/envs/gcc/datasets/csmith.py
compiler_gym-0.2.5.dist-info/LICENSE
compiler_gym-0.2.5.dist-info/METADATA
compiler_gym-0.2.5.dist-info/WHEEL
compiler_gym-0.2.5.dist-info/top_level.txt
compiler_gym-0.2.5.dist-info/RECORD
