Metadata-Version: 2.1
Name: compiler-gym
Version: 0.2.5
Summary: Reinforcement learning environments for compiler research
Home-page: https://github.com/facebookresearch/CompilerGym
Author: Facebook AI Research
License: MIT
Platform: linux-x86_64
Classifier: Development Status :: 3 - Alpha
Classifier: Environment :: Console
Classifier: Intended Audience :: Developers
Classifier: Intended Audience :: Science/Research
Classifier: License :: OSI Approved :: MIT License
Classifier: Programming Language :: Python :: 3.7
Classifier: Programming Language :: Python :: 3.8
Classifier: Programming Language :: Python :: 3.9
Classifier: Programming Language :: Python :: 3.10
Classifier: Programming Language :: Python :: 3
Classifier: Topic :: Scientific/Engineering :: Artificial Intelligence
Classifier: Topic :: Software Development :: Compilers
Requires-Python: >=3.7
License-File: LICENSE
Requires-Dist: absl-py (>=0.10.0)
Requires-Dist: deprecated (>=1.2.12)
Requires-Dist: docker (>=4.0.0)
Requires-Dist: fasteners (>=0.15)
Requires-Dist: grpcio (<1.44.0,>=1.32.0)
Requires-Dist: gym (<=0.21,>=0.18.0)
Requires-Dist: humanize (>=2.6.0)
Requires-Dist: loop-tool-py (==0.0.7)
Requires-Dist: networkx (>=2.5)
Requires-Dist: numpy (>=1.19.3)
Requires-Dist: protobuf (<4.21.0,>=3.13.0)
Requires-Dist: pydantic (>=1.8.0)
Requires-Dist: requests (>=2.24.0)
Requires-Dist: tabulate (>=0.8.7)
Requires-Dist: importlib-metadata (<5.0.0) ; python_version < "3.8"
